emagapi/__init__.py
emagapi/connect.py
emagisterapi-0.4.2.dist-info/LICENSE
emagisterapi-0.4.2.dist-info/METADATA
emagisterapi-0.4.2.dist-info/WHEEL
emagisterapi-0.4.2.dist-info/top_level.txt
emagisterapi-0.4.2.dist-info/RECORD
