Metadata-Version: 2.1
Name: emagisterapi
Version: 0.4.2
Summary: Emagister API client
Home-page: https://github.com/fdelgados/EmagisterAPI.git
Author: Cisco Delgado
Author-email: fdelgados@gmail.com
License: UNKNOWN
Platform: UNKNOWN
Classifier: Programming Language :: Python :: 3
Classifier: License :: OSI Approved :: MIT License
Classifier: Operating System :: OS Independent
Requires-Python: >=3.6
Requires-Dist: requests
Requires-Dist: numpy
